{
  "project_info": {
    "project_number": "268696056633",
    "project_id": "auth-firebase-79fb6",
    "storage_bucket": "auth-firebase-79fb6.appspot.com"
  },
  "client": [
    {
      "client_info": {
        "mobilesdk_app_id": "1:268696056633:android:5d237e8faf600f762daee8",
        "android_client_info": {
          "package_name": "id.qurban.tabunganqurban"
        }
      },
      "oauth_client": [
        {
          "client_id": "268696056633-a94ue35hqb0q0e52jh2l56iaed73haop.apps.googleusercontent.com",
          "client_type": 3
        }
      ],
      "api_key": [
        {
          "current_key": "AIzaSyB4vfB3i8c_8gcwtRLJGzNQeft4pv6kyrE"
        }
      ],
      "services": {
        "appinvite_service": {
          "other_platform_oauth_client": [
            {
              "client_id": "268696056633-a94ue35hqb0q0e52jh2l56iaed73haop.apps.googleusercontent.com",
              "client_type": 3
            }
          ]
        }
      }
    }
  ],
  "configuration_version": "1"
}